aiosqlite_strict.py
aiosqlite_strict-1.0.3.dist-info/licenses/LICENSE
aiosqlite_strict-1.0.3.dist-info/METADATA
aiosqlite_strict-1.0.3.dist-info/WHEEL
aiosqlite_strict-1.0.3.dist-info/top_level.txt
aiosqlite_strict-1.0.3.dist-info/RECORD
