Metadata-Version: 2.4
Name: aiosqlite-strict
Version: 1.0.3
Summary: aiosqlite + strict pydantic models
License: Copyright (c) 2025 Theori Inc.
Requires-Python: >=3.13
License-File: LICENSE
Requires-Dist: aiosqlite>=0.22.0
Requires-Dist: pydantic>=2.12.5
Provides-Extra: test
Requires-Dist: pytest>=8.4.2; extra == "test"
Requires-Dist: pytest-asyncio>=0.26.0; extra == "test"
Requires-Dist: pytest-cov>=6.3.0; extra == "test"
Dynamic: license-file
